psychopy_pixx/__init__.py
psychopy_pixx/calibration/_gamma_fit.py
psychopy_pixx/calibration/_s470_photometer.py
psychopy_pixx/calibration/calibration.py
psychopy_pixx/calibration/photometer.py
psychopy_pixx/devices/__init__.py
psychopy_pixx/devices/responsepixx.py
psychopy_pixx/devices/shaders/c48_frag.glsl
psychopy_pixx/devices/shaders/m16_frag.glsl
psychopy_pixx/devices/viewpixx.py
psychopy_pixx-0.1.1.dist-info/LICENSE
psychopy_pixx-0.1.1.dist-info/METADATA
psychopy_pixx-0.1.1.dist-info/WHEEL
psychopy_pixx-0.1.1.dist-info/entry_points.txt
psychopy_pixx-0.1.1.dist-info/RECORD
