Metadata-Version: 2.1
Name: psychopy-pixx
Version: 0.1.1
Summary: Psychopy plugin for high-bit luminance and VPixx devices
Home-page: https://github.com/wichmann-lab/psychopy-pixx
License: LGPL-3.0-or-later
Author: David-Elias Kuenstle
Author-email: david-elias.kuenstle@uni-tuebingen.de
Requires-Python: >=3.8,<4.0
Classifier: License :: OSI Approved :: GNU Lesser General Public License v3 or later (LGPLv3+)
Classifier: Programming Language :: Python :: 3
Classifier: Programming Language :: Python :: 3.8
Classifier: Programming Language :: Python :: 3.9
Classifier: Programming Language :: Python :: 3.10
Classifier: Programming Language :: Python :: 3.11
Requires-Dist: click (>=8.1.3,<9.0.0)
Project-URL: Repository, https://github.com/wichmann-lab/psychopy-pixx
